vis_cpu/__init__.py
vis_cpu/_utils.py
vis_cpu/_uvbeam_to_raw.py
vis_cpu/cli.py
vis_cpu/conversions.py
vis_cpu/cpu.py
vis_cpu/gpu.py
vis_cpu/plot.py
vis_cpu/wrapper.py
vis_cpu/data/NF_HERA_Dipole_small.fits
vis_cpu/gpu_src/beam_interpolation.cu
vis_cpu/gpu_src/measurement_equation.cu
vis_cpu-1.1.0.dist-info/LICENSE.txt
vis_cpu-1.1.0.dist-info/METADATA
vis_cpu-1.1.0.dist-info/WHEEL
vis_cpu-1.1.0.dist-info/entry_points.txt
vis_cpu-1.1.0.dist-info/top_level.txt
vis_cpu-1.1.0.dist-info/RECORD
