Metadata-Version: 2.1
Name: vis-cpu
Version: 1.1.0
Summary: Fast visibility simulator with interface to CPU and GPU
Home-page: https://github.com/hera-team/vis_cpu
Author: HERA-Team
Author-email: steven.g.murray@asu.edu
License: MIT
Platform: any
Classifier: Development Status :: 4 - Beta
Classifier: License :: OSI Approved :: MIT License
Classifier: Programming Language :: Python
Classifier: Programming Language :: Python :: 3
Classifier: Programming Language :: Python :: 3 :: Only
Requires-Python: >=3.9
License-File: LICENSE.txt
Requires-Dist: astropy
Requires-Dist: numpy
Requires-Dist: psutil
Requires-Dist: pyuvdata (>=2.2.8)
Requires-Dist: scipy
Provides-Extra: all
Requires-Dist: vis-cpu[dev,gpu,profile] ; extra == 'all'
Provides-Extra: dev
Requires-Dist: vis-cpu[docs,test] ; extra == 'dev'
Provides-Extra: docs
Requires-Dist: furo ; extra == 'docs'
Requires-Dist: ipython ; extra == 'docs'
Requires-Dist: nbsphinx ; extra == 'docs'
Requires-Dist: numpydoc ; extra == 'docs'
Requires-Dist: sphinx ; extra == 'docs'
Provides-Extra: gpu
Requires-Dist: jinja2 ; extra == 'gpu'
Requires-Dist: pycuda ; extra == 'gpu'
Requires-Dist: scikit-cuda ; extra == 'gpu'
Provides-Extra: profile
Requires-Dist: click ; extra == 'profile'
Requires-Dist: line-profiler ; extra == 'profile'
Requires-Dist: pyuvsim (>=1.2.5) ; extra == 'profile'
Provides-Extra: test
Requires-Dist: hypothesis ; extra == 'test'
Requires-Dist: ipython ; extra == 'test'
Requires-Dist: matplotlib ; extra == 'test'
Requires-Dist: pyradiosky ; extra == 'test'
Requires-Dist: pytest ; extra == 'test'
Requires-Dist: pytest-cov ; extra == 'test'
Requires-Dist: pyuvsim[sim] (>=1.2.5) ; extra == 'test'
